<schema  adapter="market">
	
	<element tablename="market_payment">
		<field name="objid" primary="true" prefix="MKTPMT"/>
		<field name="txndate" required="true" type="timestamp"/>
		<!-- reference to OR or receiptno number -->
		<field name="refid" required="true"/>
		<field name="reftype" required="true"/>
		<field name="refno" required="true"/>
		<field name="refdate" required="true"/>
		<field name="txnmode" required="true"/>		
		<field name="amount" required="true"/>
		<field name="voided" type="integer" datatype="checkbox" checkValue="1" uncheckValue="0"/>
	</element>


</schema>

